sorting_assistant/__about__.py
sorting_assistant/__init__.py
sorting_assistant/__main__.py
sorting_assistant/sorting_assistant.py
sorting_assistant/sorting_assistant_flet.py
sorting_assistant-0.0.3.dist-info/METADATA
sorting_assistant-0.0.3.dist-info/WHEEL
sorting_assistant-0.0.3.dist-info/entry_points.txt
sorting_assistant-0.0.3.dist-info/licenses/LICENSE.txt
sorting_assistant-0.0.3.dist-info/RECORD
