Metadata-Version: 2.3
Name: sorting-assistant
Version: 0.0.3
Summary: Tool for sorting photos based on Exif.
Project-URL: Documentation, https://github.com/adeliae1316/sorting-assistant#readme
Project-URL: Issues, https://github.com/adeliae1316/sorting-assistant/issues
Project-URL: Source, https://github.com/adeliae1316/sorting-assistant
Author-email: adeliae1316 <knsak.ug487@gmail.com>
License-Expression: MIT
License-File: LICENSE.txt
Keywords: camera,exif,exposure,photo,sorting
Classifier: Development Status :: 4 - Beta
Classifier: Programming Language :: Python
Classifier: Programming Language :: Python :: 3.8
Classifier: Programming Language :: Python :: 3.9
Classifier: Programming Language :: Python :: 3.10
Classifier: Programming Language :: Python :: 3.11
Classifier: Programming Language :: Python :: 3.12
Requires-Python: >=3.8
Requires-Dist: exif
Requires-Dist: flet
